{"name":"ShareX","tagline":"Share anything","body":"ShareX is an open source program that lets you take screenshots of any selected area with a single key, save them in your clipboard, hard disk or instantly upload them to over 25 different file hosting services. ShareX can capture screenshots with different shapes: rectangle, rounded rectangle, ellipse, triangle, diamond, polygon and also freehand. It can upload images, text files and all other different file types. It is able to capture screenshots with transparency and shadow. The program also supports clipboard upload and drag-and-drop.\r\n\r\n![ShareX](http://dl.dropbox.com/u/14076298/ShareX/2013/09/OQId4Vsbso.png)\r\n\r\n---\r\n\r\n**Capture methods:**\r\n\r\nFullscreen, Active window, Window list, Active monitor, Monitor list, Rectangle, Rectangle + Window, Rounded rectangle, Ellipse, Triangle, Diamond, Polygon, Free hand, Last region, Screen recording (Supports animated gif), Auto capture\r\n\r\n---\r\n\r\n**After capture tasks:**\r\n\r\nAdd watermark, Add border, Add shadow, Annotate image, Copy image to clipboard, Print image, Save image to file, Save image to file as, Copy file path to clipboard, Perform actions, Upload image to host\r\n\r\n---\r\n\r\n**Upload methods:**\r\n\r\nFile upload, Clipboard upload, Drag and drop, Send to from Windows Explorer, Watch folder\r\n\r\n---\r\n\r\n**After upload tasks:**\r\n\r\nUse URL shortener, Post URL to social networking service, Send URL with Email, Copy URL to clipboard\r\n\r\n---\r\n\r\n**Tools:**\r\n\r\nScreen color picker, Hash check, Index folder\r\n\r\n---\r\n\r\n**Image uploaders:**\r\n\r\nimageshack.us, tinypic.com, imgur.com, flickr.com, photobucket.com, picasaweb.google.com, uploadscreenshot.com, twitpic.com, twitsnaps.com, yfrog.com, imm.io, File uploader\r\n\r\n---\r\n\r\n**Text uploaders:**\r\n\r\npastebin.com, pastebin.ca, paste2.org, slexy.org, pastee.org, paste.ee, File uploader\r\n\r\n---\r\n\r\n**File uploaders:**\r\n\r\ndropbox.com, Google Drive, rapidshare.com, sendspace.com, minus.com, box.com, ge.tt, localhostr.com, Custom uploader, FTP server, Shared folder, Email\r\n\r\n---\r\n\r\n**URL shorteners:**\r\n\r\ngoo.gl, bit.ly, j.mp, is.gd, tinyurl.com, turl.ca\r\n\r\n---\r\n\r\n**Social networking services:**\r\n\r\ntwitter.com","google":"UA-40712139-2","note":"Don't delete this file! It's used internally to help with page regeneration."}